pura/__init__.py
pura/clipboard.py
pura/jsonfast.py
pura/notify.py
pura/py.typed
pura_utils-0.1.0.dist-info/METADATA
pura_utils-0.1.0.dist-info/WHEEL
pura_utils-0.1.0.dist-info/top_level.txt
pura_utils-0.1.0.dist-info/RECORD
