Metadata-Version: 2.4
Name: pura_utils
Version: 0.1.0
Summary: core utilities/functions
Author: purarue
License-Expression: MIT
Project-URL: Homepage, https://github.com/purarue/pura-utils
Classifier: Programming Language :: Python :: 3
Classifier: Programming Language :: Python :: 3 :: Only
Classifier: Programming Language :: Python :: 3.11
Classifier: Programming Language :: Python :: 3.12
Classifier: Programming Language :: Python :: 3.13
Classifier: Programming Language :: Python :: 3.14
Requires-Python: >=3.11
Requires-Dist: atomicwrites
Requires-Dist: beautifulsoup4
Requires-Dist: click
Requires-Dist: requests
Requires-Dist: tabulate
Requires-Dist: toml
